setup.cfg
setup.py
coollogger/TimedCompressedRotatingFileHandler.py
coollogger/__init__.py
coollogger/coollogger.py
coollogger.egg-info/PKG-INFO
coollogger.egg-info/SOURCES.txt
coollogger.egg-info/dependency_links.txt
coollogger.egg-info/top_level.txt