Metadata-Version: 1.1
Name: coollogger
Version: 1.0.1
Summary: Keep Log files zipped and cleaned.
Home-page: https://github.com/mathiasbc/CoolLogger.git
Author: Mathias Bustamante
Author-email: mathiasbc@gmail.com
License: UNKNOWN
Download-URL: https://github.com/mathiasbc/coollogger/tarball/0.0.1
Platform: UNKNOWN
